naus/__init__.py
naus-0.1.1.dist-info/METADATA
naus-0.1.1.dist-info/WHEEL
naus-0.1.1.dist-info/top_level.txt
naus-0.1.1.dist-info/RECORD
