Metadata-Version: 2.4
Name: naus
Version: 0.1.1
Summary: naus Python API
Author-email: arslee07 <mail@arslee.me>
Requires-Python: >=3.9
Requires-Dist: pyzmq
Requires-Dist: numpy
Requires-Dist: opencv-python
